{
  "@context":"http://www.w3.org/ns/csvw",
  "url":"hdb.csv",
  "tableSchema":{
    "aboutUrl":"http://ld.stadt-zuerich.ch/statistics/dataset/{ZEIT}/{RAUM}/{KENNZAHl}/{GRUPPENCODE1}/{GRUPPENCODE2}/{GRUPPENCODE3}/{GRUPPENCODE4}/{GRUPPENCODE5}",
    "null":"Dummy",
    "columns":[
      {
        "titles":"GESAMTCODE",
        "suppressOutput":true
      },
      {
        "titles":"ZEIT",
        "propertyUrl":"http://ld.stadt-zuerich.ch/statistics/property/ZEIT",
        "valueUrl":"http://ld.stadt-zuerich.ch/statistics/code/{ZEIT}"
      },
      {
        "titles":"TAG",
        "suppressOutput":true
      },
      {
        "titles":"MONAT",
        "suppressOutput":true
      },
      {
        "titles":"JAHR",
        "datatype":"gYear",
        "suppressOutput":true
      },
      {
        "titles":"RAUM",
        "propertyUrl":"http://ld.stadt-zuerich.ch/statistics/property/RAUM",
        "valueUrl":"http://ld.stadt-zuerich.ch/statistics/code/{RAUM}"
      },
      {
        "titles":"KENNZAHL",
        "propertyUrl":"http://ld.stadt-zuerich.ch/statistics/property/KENNZAHL",
        "valueUrl":"http://ld.stadt-zuerich.ch/statistics/code/{KENNZAHL}"
      },
      {
        "titles":"GRUPPE1",
        "suppressOutput":true
      },
      {
        "titles":"GRUPPENCODE1",
        "propertyUrl":"http://ld.stadt-zuerich.ch/statistics/property/{GRUPPE1}",
        "valueUrl":"http://ld.stadt-zuerich.ch/statistics/code/{GRUPPENCODE1}"
      },
      {
        "titles":"GRUPPE2",
        "suppressOutput":true
      },
      {
        "titles":"GRUPPENCODE2",
        "propertyUrl":"http://ld.stadt-zuerich.ch/statistics/property/{GRUPPE2}",
        "valueUrl":"http://ld.stadt-zuerich.ch/statistics/code/{GRUPPENCODE2}"
      },
      {
        "titles":"GRUPPE3",
        "suppressOutput":true
      },
      {
        "titles":"GRUPPENCODE3",
        "propertyUrl":"http://ld.stadt-zuerich.ch/statistics/property/{GRUPPE3}",
        "valueUrl":"http://ld.stadt-zuerich.ch/statistics/code/{GRUPPENCODE3}"
      },
      {
        "titles":"GRUPPE4",
        "suppressOutput":true
      },
      {
        "titles":"GRUPPENCODE4",
        "propertyUrl":"http://ld.stadt-zuerich.ch/statistics/property/{GRUPPE4}",
        "valueUrl":"http://ld.stadt-zuerich.ch/statistics/code/{GRUPPENCODE4}"
      },
      {
        "titles":"GRUPPE5",
        "suppressOutput":true
      },
      {
        "titles":"GRUPPENCODE5",
        "propertyUrl":"http://ld.stadt-zuerich.ch/statistics/property/{GRUPPE5}",
        "valueUrl":"http://ld.stadt-zuerich.ch/statistics/code/{GRUPPENCODE5}"
      },
      {
        "titles":"CODE",
        "suppressOutput":true
      },
      {
        "titles":"WERT",
        "datatype":"number",
        "propertyUrl":"http://ld.stadt-zuerich.ch/statistics/property/WERT"
      },
      {
        "titles":"CODENAME",
        "suppressOutput":true
      },
      {
        "titles":"KENNZAHLNAME",
        "suppressOutput":true
      },
      {
        "titles":"EINHEIT",
        "propertyUrl":"http://ld.stadt-zuerich.ch/statistics/property/EINHEIT",
        "valueUrl":"http://ld.stadt-zuerich.ch/statistics/code/{EINHEIT}"
      },
      {
        "titles":"GRUPPENAME1",
        "suppressOutput":true
      },
      {
        "titles":"GRUPPENCODENAME1",
        "suppressOutput":true
      },
      {
        "titles":"GRUPPENAME2",
        "suppressOutput":true
      },
      {
        "titles":"GRUPPENCODENAME2",
        "suppressOutput":true
      },
      {
        "titles":"GRUPPENAME3",
        "suppressOutput":true
      },
      {
        "titles":"GRUPPENCODENAME3",
        "suppressOutput":true
      },
      {
        "titles":"GRUPPENAME4",
        "suppressOutput":true
      },
      {
        "titles":"GRUPPENCODENAME4",
        "suppressOutput":true
      },
      {
        "titles":"GRUPPENAME5",
        "suppressOutput":true
      },
      {
        "titles":"GRUPPENCODENAME5",
        "suppressOutput":true
      },
      {
        "titles":"RAUMLANG",
        "suppressOutput":true
      },
      {
        "titles":"REFERENZNUMMER",
        "propertyUrl":"http://purl.org/linked-data/cube#dataSet",
        "valueUrl":"http://ld.stadt-zuerich.ch/statistics/table/{REFERENZNUMMER}"
      },
      {
        "titles":"REFERENZTITEL",
        "suppressOutput":true
      },
      {
        "titles":"ORIGINALNUMMER",
        "datatype":"number",
        "suppressOutput":true
      },
      {
        "titles":"ORIGINALTITEL",
        "suppressOutput":true
      },
      {
        "titles":"QUELLE",
        "suppressOutput":true
      },
      {
        "titles":"ELEMENT",
        "suppressOutput":true
      },
      {
        "titles":"AUSGABE",
        "suppressOutput":true
      },
      {
        "titles":"SEITE",
        "suppressOutput":true
      },
      {
        "titles":"BEMERKUNG",
        "suppressOutput":true
      },
      {
        "titles":"DATENSTAND",
        "suppressOutput":true
      },
      {
        "titles":"FREIGABE",
        "suppressOutput":true
      },
      {
        "titles":"FUSSNOTEKENNZAHL",
        "suppressOutput":true
      },
      {
        "titles":"FUSSNOTEATTRIBUT",
        "suppressOutput":true
      },
      {
        "titles":"FUSSNOTEKENNZAHLATTRIBUT",
        "suppressOutput":true
      },
      {
        "titles":"FUSSNOTEZEIT",
        "suppressOutput":true
      },
      {
        "titles":"FUSSNOTERAUM",
        "suppressOutput":true
      },
      {
        "titles":"FUSSNOTEZELLE",
        "suppressOutput":true
      },
      {
        "titles":"PUBLIKATIONSSTATUS",
        "suppressOutput":true
      },
      {
        "titles":"PUBLIKATIONSDATUM",
        "suppressOutput":true
      },
      {
        "titles":"RECORDSTATUS",
        "suppressOutput":true
      },
      {
        "titles":"SUBTHEMA",
        "suppressOutput":true
      },
      {
        "titles":"THEMA",
        "suppressOutput":true
      },
      {
        "titles":"UPDATE",
        "suppressOutput":true
      },
      {
        "virtual":true,
        "propertyUrl":"http://www.w3.org/1999/02/22-rdf-syntax-ns#type",
        "valueUrl":"http://purl.org/linked-data/cube#Observation"
      }
    ]
  }
}